LAJPAL_STT/__init__.py
jarvis_stt_god6217-0.1.dist-info/METADATA
jarvis_stt_god6217-0.1.dist-info/WHEEL
jarvis_stt_god6217-0.1.dist-info/top_level.txt
jarvis_stt_god6217-0.1.dist-info/RECORD
