Metadata-Version: 2.4
Name: jarvis-stt-god6217
Version: 0.1
Summary: this is speech to text package created by lajpal mehdi
Author: Lajpal Mehdi
Author-email: Lajpalmehdi08@gmail.com
Dynamic: author
Dynamic: author-email
Dynamic: summary
